{"Ticker": "MMM", "Company": "3M", "Sector": "Industrials", "Updated": "2022-02-17", "Rating": {"Date": "2022-02-17", "Rating": "Downgrade", "Organization": "Morgan Stanley", "Rating_Change": "Equal-Weight to Underweight", "Target_Change": "$150"}}
{"Ticker": "ADI", "Company": "Analog Devices", "Sector": "Information Technology", "Updated": "2022-02-17", "Rating": {"Date": "2022-02-17", "Rating": "Reiterated", "Organization": "UBS", "Rating_Change": "Buy", "Target_Change": "$220 to $225"}}
{"Ticker": "ADI", "Company": "Analog Devices", "Sector": "Information Technology", "Updated": "2022-02-17", "Rating": {"Date": "2022-02-17", "Rating": "Reiterated", "Organization": "Truist", "Rating_Change": "Buy", "Target_Change": "$204 to $208"}}
{"Ticker": "ADI", "Company": "Analog Devices", "Sector": "Information Technology", "Updated": "2022-02-17", "Rating": {"Date": "2022-02-17", "Rating": "Reiterated", "Organization": "Morgan Stanley", "Rating_Change": "Equal-Weight", "Target_Change": "$194 to $196"}}
{"Ticker": "ADI", "Company": "Analog Devices", "Sector": "Information Technology", "Updated": "2022-02-17", "Rating": {"Date": "2022-02-17", "Rating": "Reiterated", "Organization": "Deutsche Bank", "Rating_Change": "Hold", "Target_Change": "$200 to $185"}}
{"Ticker": "ADI", "Company": "Analog Devices", "Sector": "Information Technology", "Updated": "2022-02-17", "Rating": {"Date": "2022-02-17", "Rating": "Reiterated", "Organization": "Daiwa Securities", "Rating_Change": "Buy", "Target_Change": "$217 to $200"}}
{"Ticker": "ADI", "Company": "Analog Devices", "Sector": "Information Technology", "Updated": "2022-02-17", "Rating": {"Date": "2022-02-17", "Rating": "Reiterated", "Organization": "Citigroup", "Rating_Change": "Buy", "Target_Change": "$216 to $192"}}
{"Ticker": "AMAT", "Company": "Applied Materials", "Sector": "Information Technology", "Updated": "2022-02-17", "Rating": {"Date": "2022-02-17", "Rating": "Reiterated", "Organization": "UBS", "Rating_Change": "Neutral", "Target_Change": "$150 to $160"}}
{"Ticker": "AMAT", "Company": "Applied Materials", "Sector": "Information Technology", "Updated": "2022-02-17", "Rating": {"Date": "2022-02-17", "Rating": "Reiterated", "Organization": "Piper Sandler", "Rating_Change": "Neutral", "Target_Change": "$158 to $153"}}
{"Ticker": "AMAT", "Company": "Applied Materials", "Sector": "Information Technology", "Updated": "2022-02-17", "Rating": {"Date": "2022-02-17", "Rating": "Reiterated", "Organization": "Needham", "Rating_Change": "Buy", "Target_Change": "$166 to $172"}}
{"Ticker": "AMAT", "Company": "Applied Materials", "Sector": "Information Technology", "Updated": "2022-02-17", "Rating": {"Date": "2022-02-17", "Rating": "Reiterated", "Organization": "Mizuho", "Rating_Change": "Buy", "Target_Change": "$178 to $180"}}
{"Ticker": "ADSK", "Company": "Autodesk", "Sector": "Information Technology", "Updated": "2022-02-17", "Rating": {"Date": "2022-02-17", "Rating": "Resumed", "Organization": "Citigroup", "Rating_Change": "Buy", "Target_Change": "$305"}}
{"Ticker": "CNP", "Company": "CenterPoint Energy", "Sector": "Utilities", "Updated": "2022-02-17", "Rating": {"Date": "2022-02-17", "Rating": "Resumed", "Organization": "Morgan Stanley", "Rating_Change": "Overweight", "Target_Change": "$30"}}
{"Ticker": "CF", "Company": "CF Industries", "Sector": "Materials", "Updated": "2022-02-17", "Rating": {"Date": "2022-02-17", "Rating": "Downgrade", "Organization": "JP Morgan", "Rating_Change": "Overweight to Neutral", "Target_Change": "$70 to $75"}}
{"Ticker": "CRL", "Company": "Charles River Laboratories", "Sector": "Health Care", "Updated": "2022-02-17", "Rating": {"Date": "2022-02-17", "Rating": "Upgrade", "Organization": "Citigroup", "Rating_Change": "Neutral to Buy", "Target_Change": "$400"}}
{"Ticker": "CRL", "Company": "Charles River Laboratories", "Sector": "Health Care", "Updated": "2022-02-17", "Rating": {"Date": "2022-02-17", "Rating": "Reiterated", "Organization": "UBS", "Rating_Change": "Buy", "Target_Change": "$465 to $420"}}
{"Ticker": "CRL", "Company": "Charles River Laboratories", "Sector": "Health Care", "Updated": "2022-02-17", "Rating": {"Date": "2022-02-17", "Rating": "Reiterated", "Organization": "Morgan Stanley", "Rating_Change": "Overweight", "Target_Change": "$465 to $430"}}
{"Ticker": "CRL", "Company": "Charles River Laboratories", "Sector": "Health Care", "Updated": "2022-02-17", "Rating": {"Date": "2022-02-17", "Rating": "Reiterated", "Organization": "Deutsche Bank", "Rating_Change": "Buy", "Target_Change": "$409 to $350"}}
{"Ticker": "CRL", "Company": "Charles River Laboratories", "Sector": "Health Care", "Updated": "2022-02-17", "Rating": {"Date": "2022-02-17", "Rating": "Reiterated", "Organization": "BofA Securities", "Rating_Change": "Buy", "Target_Change": "$445 to $400"}}
{"Ticker": "ED", "Company": "Consolidated Edison", "Sector": "Utilities", "Updated": "2022-02-17", "Rating": {"Date": "2022-02-17", "Rating": "Upgrade", "Organization": "Wolfe Research", "Rating_Change": "Underperform to Peer Perform", "Target_Change": "$82"}}
{"Ticker": "EQIX", "Company": "Equinix", "Sector": "Real Estate", "Updated": "2022-02-17", "Rating": {"Date": "2022-02-17", "Rating": "Upgrade", "Organization": "TD Securities", "Rating_Change": "Hold to Buy", "Target_Change": "$900 to $850"}}
{"Ticker": "GNRC", "Company": "Generac Holdings", "Sector": "Industrials", "Updated": "2022-02-17", "Rating": {"Date": "2022-02-17", "Rating": "Reiterated", "Organization": "Oppenheimer", "Rating_Change": "Outperform", "Target_Change": "$540 to $450"}}
{"Ticker": "GNRC", "Company": "Generac Holdings", "Sector": "Industrials", "Updated": "2022-02-17", "Rating": {"Date": "2022-02-17", "Rating": "Reiterated", "Organization": "KeyBanc Capital Markets", "Rating_Change": "Overweight", "Target_Change": "$500 to $435"}}
{"Ticker": "GNRC", "Company": "Generac Holdings", "Sector": "Industrials", "Updated": "2022-02-17", "Rating": {"Date": "2022-02-17", "Rating": "Reiterated", "Organization": "Citigroup", "Rating_Change": "Buy", "Target_Change": "$375 to $380"}}
{"Ticker": "GNRC", "Company": "Generac Holdings", "Sector": "Industrials", "Updated": "2022-02-17", "Rating": {"Date": "2022-02-17", "Rating": "Reiterated", "Organization": "Canaccord Genuity", "Rating_Change": "Buy", "Target_Change": "$575 to $556"}}
{"Ticker": "HLT", "Company": "Hilton Worldwide", "Sector": "Consumer Discretionary", "Updated": "2022-02-17", "Rating": {"Date": "2022-02-17", "Rating": "Reiterated", "Organization": "Truist", "Rating_Change": "Hold", "Target_Change": "$139 to $152"}}
{"Ticker": "HLT", "Company": "Hilton Worldwide", "Sector": "Consumer Discretionary", "Updated": "2022-02-17", "Rating": {"Date": "2022-02-17", "Rating": "Reiterated", "Organization": "Morgan Stanley", "Rating_Change": "Equal-Weight", "Target_Change": "$135 to $136"}}
{"Ticker": "HLT", "Company": "Hilton Worldwide", "Sector": "Consumer Discretionary", "Updated": "2022-02-17", "Rating": {"Date": "2022-02-17", "Rating": "Reiterated", "Organization": "Jefferies", "Rating_Change": "Buy", "Target_Change": "$169 to $179"}}
{"Ticker": "HLT", "Company": "Hilton Worldwide", "Sector": "Consumer Discretionary", "Updated": "2022-02-17", "Rating": {"Date": "2022-02-17", "Rating": "Reiterated", "Organization": "Deutsche Bank", "Rating_Change": "Hold", "Target_Change": "$126 to $136"}}
{"Ticker": "MKC", "Company": "McCormick & Company", "Sector": "Consumer Staples", "Updated": "2022-02-17", "Rating": {"Date": "2022-02-17", "Rating": "Upgrade", "Organization": "Argus", "Rating_Change": "Hold to Buy", "Target_Change": "$112"}}
{"Ticker": "MNST", "Company": "Monster Beverage", "Sector": "Consumer Staples", "Updated": "2022-02-17", "Rating": {"Date": "2022-02-17", "Rating": "Initiated", "Organization": "BMO Capital Markets", "Rating_Change": "Market Perform", "Target_Change": "$92"}}
{"Ticker": "NVDA", "Company": "Nvidia", "Sector": "Information Technology", "Updated": "2022-02-17", "Rating": {"Date": "2022-02-17", "Rating": "Downgrade", "Organization": "Summit Insights", "Rating_Change": "Buy to Hold", "Target_Change": ""}}
{"Ticker": "PKG", "Company": "Packaging Corporation of America", "Sector": "Materials", "Updated": "2022-02-17", "Rating": {"Date": "2022-02-17", "Rating": "Upgrade", "Organization": "UBS", "Rating_Change": "Sell to Neutral", "Target_Change": "$127 to $154"}}
{"Ticker": "PVH", "Company": "PVH", "Sector": "Consumer Discretionary", "Updated": "2022-02-17", "Rating": {"Date": "2022-02-17", "Rating": "Resumed", "Organization": "BofA Securities", "Rating_Change": "Buy", "Target_Change": "$156"}}
{"Ticker": "YUM", "Company": "Yum! Brands", "Sector": "Consumer Discretionary", "Updated": "2022-02-17", "Rating": {"Date": "2022-02-17", "Rating": "Upgrade", "Organization": "Cowen", "Rating_Change": "Market Perform to Outperform", "Target_Change": "$134 to $143"}}
