{"Ticker": "AAP", "Company": "Advance Auto Parts", "Sector": "Consumer Discretionary", "Updated": "2022-01-28", "Rating": {"Date": "2022-01-28", "Rating": "Initiated", "Organization": "RBC Capital Mkts", "Rating_Change": "Sector Perform", "Target_Change": "$239"}}
{"Ticker": "AAPL", "Company": "Apple", "Sector": "Information Technology", "Updated": "2022-01-28", "Rating": {"Date": "2022-01-28", "Rating": "Upgrade", "Organization": "New Street", "Rating_Change": "Sell to Neutral", "Target_Change": "$165"}}
{"Ticker": "AAPL", "Company": "Apple", "Sector": "Information Technology", "Updated": "2022-01-28", "Rating": {"Date": "2022-01-28", "Rating": "Reiterated", "Organization": "Monness Crespi & Hardt", "Rating_Change": "Buy", "Target_Change": "$184 to $199"}}
{"Ticker": "BIO", "Company": "Bio-Rad Laboratories", "Sector": "Health Care", "Updated": "2022-01-28", "Rating": {"Date": "2022-01-28", "Rating": "Reiterated", "Organization": "Citigroup", "Rating_Change": "Buy", "Target_Change": "$915 to $750"}}
{"Ticker": "CHRW", "Company": "C. H. Robinson", "Sector": "Industrials", "Updated": "2022-01-28", "Rating": {"Date": "2022-01-28", "Rating": "Initiated", "Organization": "The Benchmark Company", "Rating_Change": "Buy", "Target_Change": "$125"}}
{"Ticker": "KMX", "Company": "CarMax", "Sector": "Consumer Discretionary", "Updated": "2022-01-28", "Rating": {"Date": "2022-01-28", "Rating": "Resumed", "Organization": "RBC Capital Mkts", "Rating_Change": "Outperform", "Target_Change": "$157 to $140"}}
{"Ticker": "GLW", "Company": "Corning", "Sector": "Information Technology", "Updated": "2022-01-28", "Rating": {"Date": "2022-01-28", "Rating": "Upgrade", "Organization": "Susquehanna", "Rating_Change": "Neutral to Positive", "Target_Change": "$38 to $50"}}
{"Ticker": "CCI", "Company": "Crown Castle", "Sector": "Real Estate", "Updated": "2022-01-28", "Rating": {"Date": "2022-01-28", "Rating": "Upgrade", "Organization": "Raymond James", "Rating_Change": "Mkt Perform to Outperform", "Target_Change": "$184"}}
{"Ticker": "GD", "Company": "General Dynamics", "Sector": "Industrials", "Updated": "2022-01-28", "Rating": {"Date": "2022-01-28", "Rating": "Upgrade", "Organization": "Wolfe Research", "Rating_Change": "Underperform to Peer Perform", "Target_Change": ""}}
{"Ticker": "GILD", "Company": "Gilead Sciences", "Sector": "Health Care", "Updated": "2022-01-28", "Rating": {"Date": "2022-01-28", "Rating": "Upgrade", "Organization": "Argus", "Rating_Change": "Hold to Buy", "Target_Change": ""}}
{"Ticker": "GS", "Company": "Goldman Sachs", "Sector": "Financials", "Updated": "2022-01-28", "Rating": {"Date": "2022-01-28", "Rating": "Downgrade", "Organization": "Odeon", "Rating_Change": "Buy to Hold", "Target_Change": ""}}
{"Ticker": "IP", "Company": "International Paper", "Sector": "Materials", "Updated": "2022-01-28", "Rating": {"Date": "2022-01-28", "Rating": "Downgrade", "Organization": "Seaport Research Partners", "Rating_Change": "Buy to Neutral", "Target_Change": ""}}
{"Ticker": "KR", "Company": "Kroger", "Sector": "Consumer Staples", "Updated": "2022-01-28", "Rating": {"Date": "2022-01-28", "Rating": "Downgrade", "Organization": "Citigroup", "Rating_Change": "Neutral to Sell", "Target_Change": "$47 to $42"}}
{"Ticker": "LH", "Company": "LabCorp", "Sector": "Health Care", "Updated": "2022-01-28", "Rating": {"Date": "2022-01-28", "Rating": "Downgrade", "Organization": "Deutsche Bank", "Rating_Change": "Buy to Hold", "Target_Change": "$330 to $294"}}
{"Ticker": "MS", "Company": "Morgan Stanley", "Sector": "Financials", "Updated": "2022-01-28", "Rating": {"Date": "2022-01-28", "Rating": "Downgrade", "Organization": "Odeon", "Rating_Change": "Buy to Hold", "Target_Change": ""}}
{"Ticker": "NLSN", "Company": "Nielsen Holdings", "Sector": "Industrials", "Updated": "2022-01-28", "Rating": {"Date": "2022-01-28", "Rating": "Downgrade", "Organization": "Truist", "Rating_Change": "Buy to Hold", "Target_Change": "$25 to $22"}}
{"Ticker": "ORLY", "Company": "O'Reilly Automotive", "Sector": "Consumer Discretionary", "Updated": "2022-01-28", "Rating": {"Date": "2022-01-28", "Rating": "Initiated", "Organization": "RBC Capital Mkts", "Rating_Change": "Outperform", "Target_Change": "$755"}}
{"Ticker": "PKG", "Company": "Packaging Corporation of America", "Sector": "Materials", "Updated": "2022-01-28", "Rating": {"Date": "2022-01-28", "Rating": "Upgrade", "Organization": "Seaport Research Partners", "Rating_Change": "Neutral to Buy", "Target_Change": "$176"}}
{"Ticker": "DGX", "Company": "Quest Diagnostics", "Sector": "Health Care", "Updated": "2022-01-28", "Rating": {"Date": "2022-01-28", "Rating": "Downgrade", "Organization": "Deutsche Bank", "Rating_Change": "Buy to Hold", "Target_Change": "$190 to $129"}}
{"Ticker": "RJF", "Company": "Raymond James Financial", "Sector": "Financials", "Updated": "2022-01-28", "Rating": {"Date": "2022-01-28", "Rating": "Upgrade", "Organization": "Seaport Research Partners", "Rating_Change": "Neutral to Buy", "Target_Change": "$125"}}
{"Ticker": "RMD", "Company": "ResMed", "Sector": "Health Care", "Updated": "2022-01-28", "Rating": {"Date": "2022-01-28", "Rating": "Upgrade", "Organization": "RBC Capital Mkts", "Rating_Change": "Underperform to Sector Perform", "Target_Change": "$234 to $241"}}
{"Ticker": "SEE", "Company": "Sealed Air", "Sector": "Materials", "Updated": "2022-01-28", "Rating": {"Date": "2022-01-28", "Rating": "Initiated", "Organization": "Credit Suisse", "Rating_Change": "Outperform", "Target_Change": "$80"}}
{"Ticker": "TPR", "Company": "Tapestry", "Sector": "Consumer Discretionary", "Updated": "2022-01-28", "Rating": {"Date": "2022-01-28", "Rating": "Upgrade", "Organization": "Citigroup", "Rating_Change": "Neutral to Buy", "Target_Change": "$50 to $48"}}
{"Ticker": "TGT", "Company": "Target Corporation", "Sector": "Consumer Discretionary", "Updated": "2022-01-28", "Rating": {"Date": "2022-01-28", "Rating": "Initiated", "Organization": "RBC Capital Mkts", "Rating_Change": "Outperform", "Target_Change": "$278"}}
{"Ticker": "TER", "Company": "Teradyne", "Sector": "Information Technology", "Updated": "2022-01-28", "Rating": {"Date": "2022-01-28", "Rating": "Upgrade", "Organization": "Craig Hallum", "Rating_Change": "Hold to Buy", "Target_Change": "$138"}}
{"Ticker": "TER", "Company": "Teradyne", "Sector": "Information Technology", "Updated": "2022-01-28", "Rating": {"Date": "2022-01-28", "Rating": "Downgrade", "Organization": "Stifel", "Rating_Change": "Buy to Hold", "Target_Change": "$160 to $115"}}
{"Ticker": "TER", "Company": "Teradyne", "Sector": "Information Technology", "Updated": "2022-01-28", "Rating": {"Date": "2022-01-28", "Rating": "Downgrade", "Organization": "Deutsche Bank", "Rating_Change": "Buy to Hold", "Target_Change": "$170 to $120"}}
{"Ticker": "TSCO", "Company": "Tractor Supply Company", "Sector": "Consumer Discretionary", "Updated": "2022-01-28", "Rating": {"Date": "2022-01-28", "Rating": "Upgrade", "Organization": "Citigroup", "Rating_Change": "Neutral to Buy", "Target_Change": "$230 to $240"}}
{"Ticker": "WMT", "Company": "Walmart", "Sector": "Consumer Staples", "Updated": "2022-01-28", "Rating": {"Date": "2022-01-28", "Rating": "Initiated", "Organization": "RBC Capital Mkts", "Rating_Change": "Outperform", "Target_Change": "$160"}}
