{"Ticker": "ALK", "Company": "Alaska Air Group", "Sector": "Industrials", "Updated": "2022-02-15", "Rating": {"Date": "2022-02-15", "Rating": "Resumed", "Organization": "Wolfe Research", "Rating_Change": "Outperform", "Target_Change": "$67"}}
{"Ticker": "AAL", "Company": "American Airlines Group", "Sector": "Industrials", "Updated": "2022-02-15", "Rating": {"Date": "2022-02-15", "Rating": "Resumed", "Organization": "Wolfe Research", "Rating_Change": "Outperform", "Target_Change": ""}}
{"Ticker": "CBOE", "Company": "Cboe Global Markets", "Sector": "Financials", "Updated": "2022-02-15", "Rating": {"Date": "2022-02-15", "Rating": "Initiated", "Organization": "Credit Suisse", "Rating_Change": "Neutral", "Target_Change": "$144"}}
{"Ticker": "CME", "Company": "CME Group", "Sector": "Financials", "Updated": "2022-02-15", "Rating": {"Date": "2022-02-15", "Rating": "Initiated", "Organization": "Credit Suisse", "Rating_Change": "Neutral", "Target_Change": "$258"}}
{"Ticker": "DAL", "Company": "Delta Air Lines", "Sector": "Industrials", "Updated": "2022-02-15", "Rating": {"Date": "2022-02-15", "Rating": "Resumed", "Organization": "Wolfe Research", "Rating_Change": "Outperform", "Target_Change": "$50"}}
{"Ticker": "DTE", "Company": "DTE Energy", "Sector": "Utilities", "Updated": "2022-02-15", "Rating": {"Date": "2022-02-15", "Rating": "Upgrade", "Organization": "BofA Securities", "Rating_Change": "Underperform to Buy", "Target_Change": "$127"}}
{"Ticker": "GPS", "Company": "Gap", "Sector": "Consumer Discretionary", "Updated": "2022-02-15", "Rating": {"Date": "2022-02-15", "Rating": "Downgrade", "Organization": "BofA Securities", "Rating_Change": "Neutral to Underperform", "Target_Change": "$26 to $14"}}
{"Ticker": "ICE", "Company": "Intercontinental Exchange", "Sector": "Financials", "Updated": "2022-02-15", "Rating": {"Date": "2022-02-15", "Rating": "Initiated", "Organization": "Credit Suisse", "Rating_Change": "Outperform", "Target_Change": "$160"}}
{"Ticker": "MKTX", "Company": "MarketAxess", "Sector": "Financials", "Updated": "2022-02-15", "Rating": {"Date": "2022-02-15", "Rating": "Initiated", "Organization": "Credit Suisse", "Rating_Change": "Neutral", "Target_Change": "$412"}}
{"Ticker": "NDAQ", "Company": "Nasdaq", "Sector": "Financials", "Updated": "2022-02-15", "Rating": {"Date": "2022-02-15", "Rating": "Initiated", "Organization": "Credit Suisse", "Rating_Change": "Outperform", "Target_Change": "$225"}}
{"Ticker": "NI", "Company": "NiSource", "Sector": "Utilities", "Updated": "2022-02-15", "Rating": {"Date": "2022-02-15", "Rating": "Downgrade", "Organization": "UBS", "Rating_Change": "Buy to Neutral", "Target_Change": "$29 to $31"}}
{"Ticker": "PEP", "Company": "PepsiCo", "Sector": "Consumer Staples", "Updated": "2022-02-15", "Rating": {"Date": "2022-02-15", "Rating": "Downgrade", "Organization": "DZ Bank", "Rating_Change": "Buy to Hold", "Target_Change": "$180"}}
{"Ticker": "LUV", "Company": "Southwest Airlines", "Sector": "Industrials", "Updated": "2022-02-15", "Rating": {"Date": "2022-02-15", "Rating": "Resumed", "Organization": "Wolfe Research", "Rating_Change": "Peer Perform", "Target_Change": ""}}
{"Ticker": "UAL", "Company": "United Airlines", "Sector": "Industrials", "Updated": "2022-02-15", "Rating": {"Date": "2022-02-15", "Rating": "Resumed", "Organization": "Wolfe Research", "Rating_Change": "Underperform", "Target_Change": ""}}
