{"Ticker": "CDAY", "Company": "Ceridian", "Sector": "Information Technology", "Updated": "2022-09-01", "Rating": {"Date": "2022-09-01", "Rating": "Initiated", "Organization": "Citigroup", "Rating_Change": "Buy", "Target_Change": "$73"}}
{"Ticker": "HPQ", "Company": "HP", "Sector": "Information Technology", "Updated": "2022-09-01", "Rating": {"Date": "2022-09-01", "Rating": "Downgrade", "Organization": "Loop Capital", "Rating_Change": "Buy to Hold", "Target_Change": "$50 to $29"}}
{"Ticker": "INTU", "Company": "Intuit", "Sector": "Information Technology", "Updated": "2022-09-01", "Rating": {"Date": "2022-09-01", "Rating": "Initiated", "Organization": "Citigroup", "Rating_Change": "Buy", "Target_Change": "$538"}}
{"Ticker": "TAP", "Company": "Molson Coors Beverage Company", "Sector": "Consumer Staples", "Updated": "2022-09-01", "Rating": {"Date": "2022-09-01", "Rating": "Downgrade", "Organization": "Bryan Garnier", "Rating_Change": "Buy to Sell", "Target_Change": "$54"}}
{"Ticker": "PAYC", "Company": "Paycom", "Sector": "Information Technology", "Updated": "2022-09-01", "Rating": {"Date": "2022-09-01", "Rating": "Initiated", "Organization": "Citigroup", "Rating_Change": "Buy", "Target_Change": "$457"}}
{"Ticker": "STX", "Company": "Seagate Technology", "Sector": "Information Technology", "Updated": "2022-09-01", "Rating": {"Date": "2022-09-01", "Rating": "Downgrade", "Organization": "The Benchmark Company", "Rating_Change": "Buy to Hold", "Target_Change": ""}}
{"Ticker": "VMC", "Company": "Vulcan Materials", "Sector": "Materials", "Updated": "2022-09-01", "Rating": {"Date": "2022-09-01", "Rating": "Upgrade", "Organization": "Vertical Research", "Rating_Change": "Hold to Buy", "Target_Change": "$225"}}
{"Ticker": "WDC", "Company": "Western Digital", "Sector": "Information Technology", "Updated": "2022-09-01", "Rating": {"Date": "2022-09-01", "Rating": "Downgrade", "Organization": "The Benchmark Company", "Rating_Change": "Hold to Sell", "Target_Change": "$34"}}
