{"Ticker": "AOS", "Company": "A. O. Smith", "Sector": "Industrials", "Updated": "2022-07-06", "Rating": {"Date": "2022-07-06", "Rating": "Upgrade", "Organization": "Longbow", "Rating_Change": "Neutral to Buy", "Target_Change": "$71"}}
{"Ticker": "ABT", "Company": "Abbott Laboratories", "Sector": "Health Care", "Updated": "2022-07-06", "Rating": {"Date": "2022-07-06", "Rating": "Initiated", "Organization": "Wolfe Research", "Rating_Change": "Underperform", "Target_Change": "$95"}}
{"Ticker": "AAPL", "Company": "Apple", "Sector": "Information Technology", "Updated": "2022-07-06", "Rating": {"Date": "2022-07-06", "Rating": "Reiterated", "Organization": "Goldman", "Rating_Change": "Neutral", "Target_Change": "$157 to $130"}}
{"Ticker": "BSX", "Company": "Boston Scientific", "Sector": "Health Care", "Updated": "2022-07-06", "Rating": {"Date": "2022-07-06", "Rating": "Initiated", "Organization": "Wolfe Research", "Rating_Change": "Outperform", "Target_Change": "$43"}}
{"Ticker": "EOG", "Company": "EOG Resources", "Sector": "Energy", "Updated": "2022-07-06", "Rating": {"Date": "2022-07-06", "Rating": "Downgrade", "Organization": "RBC Capital Mkts", "Rating_Change": "Outperform to Sector Perform", "Target_Change": "$150"}}
{"Ticker": "HCA", "Company": "HCA Healthcare", "Sector": "Health Care", "Updated": "2022-07-06", "Rating": {"Date": "2022-07-06", "Rating": "Downgrade", "Organization": "BMO Capital Markets", "Rating_Change": "Market Perform to Underperform", "Target_Change": "$233 to $160"}}
{"Ticker": "HWM", "Company": "Howmet Aerospace", "Sector": "Industrials", "Updated": "2022-07-06", "Rating": {"Date": "2022-07-06", "Rating": "Initiated", "Organization": "Truist", "Rating_Change": "Buy", "Target_Change": "$41"}}
{"Ticker": "MKC", "Company": "McCormick & Company", "Sector": "Consumer Staples", "Updated": "2022-07-06", "Rating": {"Date": "2022-07-06", "Rating": "Downgrade", "Organization": "Argus", "Rating_Change": "Buy to Hold", "Target_Change": ""}}
{"Ticker": "MCK", "Company": "McKesson Corporation", "Sector": "Health Care", "Updated": "2022-07-06", "Rating": {"Date": "2022-07-06", "Rating": "Downgrade", "Organization": "Argus", "Rating_Change": "Buy to Hold", "Target_Change": ""}}
{"Ticker": "MDT", "Company": "Medtronic", "Sector": "Health Care", "Updated": "2022-07-06", "Rating": {"Date": "2022-07-06", "Rating": "Initiated", "Organization": "Wolfe Research", "Rating_Change": "Underperform", "Target_Change": "$85"}}
{"Ticker": "MRK", "Company": "Merck & Co.", "Sector": "Health Care", "Updated": "2022-07-06", "Rating": {"Date": "2022-07-06", "Rating": "Upgrade", "Organization": "Daiwa Securities", "Rating_Change": "Neutral to Buy", "Target_Change": "$89 to $102"}}
{"Ticker": "NFLX", "Company": "Netflix", "Sector": "Communication Services", "Updated": "2022-07-06", "Rating": {"Date": "2022-07-06", "Rating": "Reiterated", "Organization": "Barclays", "Rating_Change": "Equal Weight", "Target_Change": "$275 to $170"}}
{"Ticker": "PXD", "Company": "Pioneer Natural Resources", "Sector": "Energy", "Updated": "2022-07-06", "Rating": {"Date": "2022-07-06", "Rating": "Downgrade", "Organization": "RBC Capital Mkts", "Rating_Change": "Outperform to Sector Perform", "Target_Change": "$290"}}
{"Ticker": "SRE", "Company": "Sempra Energy", "Sector": "Utilities", "Updated": "2022-07-06", "Rating": {"Date": "2022-07-06", "Rating": "Upgrade", "Organization": "Goldman", "Rating_Change": "Neutral to Buy", "Target_Change": "$164 to $167"}}
{"Ticker": "TFX", "Company": "Teleflex", "Sector": "Health Care", "Updated": "2022-07-06", "Rating": {"Date": "2022-07-06", "Rating": "Initiated", "Organization": "Wolfe Research", "Rating_Change": "Outperform", "Target_Change": "$300"}}
{"Ticker": "UNP", "Company": "Union Pacific", "Sector": "Industrials", "Updated": "2022-07-06", "Rating": {"Date": "2022-07-06", "Rating": "Downgrade", "Organization": "Susquehanna", "Rating_Change": "Positive to Neutral", "Target_Change": "$235"}}
{"Ticker": "UHS", "Company": "Universal Health Services", "Sector": "Health Care", "Updated": "2022-07-06", "Rating": {"Date": "2022-07-06", "Rating": "Downgrade", "Organization": "BMO Capital Markets", "Rating_Change": "Market Perform to Underperform", "Target_Change": "$133 to $90"}}
