{"Ticker": "CL", "Company": "Colgate-Palmolive", "Sector": "Consumer Staples", "Updated": "2021-12-30 12:05:22", "Rating": [{"Date": "2021-12-16", "Rating": "Initiated", "Organization": "Redburn", "Rating_Change": "Neutral", "Target_Change": ""}, {"Date": "2021-10-05", "Rating": "Resumed", "Organization": "BofA Securities", "Rating_Change": "Neutral", "Target_Change": "$80"}, {"Date": "2021-09-20", "Rating": "Upgrade", "Organization": "Deutsche Bank", "Rating_Change": "Hold to Buy", "Target_Change": "$84 to $86"}, {"Date": "2021-06-24", "Rating": "Initiated", "Organization": "UBS", "Rating_Change": "Buy", "Target_Change": "$95"}, {"Date": "2021-06-09", "Rating": "Upgrade", "Organization": "Credit Suisse", "Rating_Change": "Neutral to Outperform", "Target_Change": "$80 to $95"}, {"Date": "2021-02-01", "Rating": "Upgrade", "Organization": "Credit Suisse", "Rating_Change": "Underperform to Neutral", "Target_Change": "$70 to $80"}, {"Date": "2021-01-28", "Rating": "Downgrade", "Organization": "Stifel", "Rating_Change": "Buy to Hold", "Target_Change": "$83"}, {"Date": "2021-01-26", "Rating": "Upgrade", "Organization": "Berenberg", "Rating_Change": "Sell to Hold", "Target_Change": ""}, {"Date": "2021-01-20", "Rating": "Initiated", "Organization": "Bernstein", "Rating_Change": "Underperform", "Target_Change": "$77"}, {"Date": "2021-01-04", "Rating": "Downgrade", "Organization": "RBC Capital Mkts", "Rating_Change": "Outperform to Sector Perform", "Target_Change": "$90"}, {"Date": "2020-12-08", "Rating": "Initiated", "Organization": "Wells Fargo", "Rating_Change": "Underweight", "Target_Change": "$80"}, {"Date": "2020-07-22", "Rating": "Downgrade", "Organization": "Morgan Stanley", "Rating_Change": "Overweight to Equal-Weight", "Target_Change": "$78"}, {"Date": "2020-03-27", "Rating": "Upgrade", "Organization": "SunTrust", "Rating_Change": "Hold to Buy", "Target_Change": ""}, {"Date": "2020-03-27", "Rating": "Upgrade", "Organization": "Stifel", "Rating_Change": "Hold to Buy", "Target_Change": "$80 to $72"}, {"Date": "2020-03-23", "Rating": "Upgrade", "Organization": "Morgan Stanley", "Rating_Change": "Equal-Weight to Overweight", "Target_Change": "$72"}, {"Date": "2020-03-20", "Rating": "Upgrade", "Organization": "BofA/Merrill", "Rating_Change": "Neutral to Buy", "Target_Change": ""}, {"Date": "2020-02-03", "Rating": "Upgrade", "Organization": "RBC Capital Mkts", "Rating_Change": "Sector Perform to Outperform", "Target_Change": ""}, {"Date": "2020-02-03", "Rating": "Upgrade", "Organization": "Atlantic Equities", "Rating_Change": "Neutral to Overweight", "Target_Change": ""}, {"Date": "2019-12-19", "Rating": "Downgrade", "Organization": "BofA/Merrill", "Rating_Change": "Buy to Neutral", "Target_Change": "$77 to $74"}, {"Date": "2019-10-16", "Rating": "Initiated", "Organization": "Berenberg", "Rating_Change": "Sell", "Target_Change": "$58"}]}