{"Ticker": "RL", "Company": "Ralph Lauren Corporation", "Sector": "Consumer Discretionary", "Updated": "2023-09-18", "Rating": [{"Date": "2023-09-18", "Rating": "Upgrade", "Organization": "Guggenheim", "Rating_Change": "Neutral to Buy", "Target_Change": "$166"}, {"Date": "2023-02-13", "Rating": "Upgrade", "Organization": "BofA Securities", "Rating_Change": "Neutral to Buy", "Target_Change": "$130 to $145"}, {"Date": "2023-01-27", "Rating": "Downgrade", "Organization": "BMO Capital Markets", "Rating_Change": "Market Perform to Underperform", "Target_Change": "$100"}, {"Date": "2023-01-20", "Rating": "Upgrade", "Organization": "Barclays", "Rating_Change": "Equal Weight to Overweight", "Target_Change": "$101 to $134"}, {"Date": "2022-05-23", "Rating": "Downgrade", "Organization": "Citigroup", "Rating_Change": "Buy to Neutral", "Target_Change": "$140 to $98"}, {"Date": "2022-04-05", "Rating": "Downgrade", "Organization": "Wells Fargo", "Rating_Change": "Overweight to Equal Weight", "Target_Change": "$135 to $110"}, {"Date": "2022-03-17", "Rating": "Upgrade", "Organization": "JP Morgan", "Rating_Change": "Neutral to Overweight", "Target_Change": "$142"}, {"Date": "2022-03-07", "Rating": "Downgrade", "Organization": "Wedbush", "Rating_Change": "Outperform to Neutral", "Target_Change": "$150 to $127"}, {"Date": "2021-12-16", "Rating": "Initiated", "Organization": "Truist", "Rating_Change": "Buy", "Target_Change": "$141"}, {"Date": "2021-12-14", "Rating": "Downgrade", "Organization": "Goldman", "Rating_Change": "Buy to Sell", "Target_Change": "$142 to $110"}, {"Date": "2021-10-05", "Rating": "Initiated", "Organization": "Wedbush", "Rating_Change": "Outperform", "Target_Change": "$137"}, {"Date": "2021-07-14", "Rating": "Initiated", "Organization": "Goldman", "Rating_Change": "Buy", "Target_Change": "$147"}, {"Date": "2021-04-28", "Rating": "Upgrade", "Organization": "Cowen", "Rating_Change": "Market Perform to Outperform", "Target_Change": "$110 to $152"}, {"Date": "2021-04-23", "Rating": "Resumed", "Organization": "RBC Capital Mkts", "Rating_Change": "Outperform", "Target_Change": "$138"}, {"Date": "2021-02-17", "Rating": "Reiterated", "Organization": "Telsey Advisory Group", "Rating_Change": "Outperform", "Target_Change": "$120 to $130"}, {"Date": "2021-02-01", "Rating": "Reiterated", "Organization": "Needham", "Rating_Change": "Buy", "Target_Change": "$82 to $112"}, {"Date": "2021-01-29", "Rating": "Reiterated", "Organization": "Telsey Advisory Group", "Rating_Change": "Outperform", "Target_Change": "$88 to $120"}, {"Date": "2021-01-15", "Rating": "Upgrade", "Organization": "RBC Capital Mkts", "Rating_Change": "Sector Perform to Outperform", "Target_Change": "$77 to $138"}, {"Date": "2021-01-11", "Rating": "Upgrade", "Organization": "UBS", "Rating_Change": "Neutral to Buy", "Target_Change": ""}, {"Date": "2020-12-11", "Rating": "Upgrade", "Organization": "Citigroup", "Rating_Change": "Neutral to Buy", "Target_Change": "$134"}, {"Date": "2020-12-10", "Rating": "Upgrade", "Organization": "Goldman", "Rating_Change": "Sell to Buy", "Target_Change": "$69 to $141"}, {"Date": "2020-11-10", "Rating": "Downgrade", "Organization": "BofA Securities", "Rating_Change": "Buy to Neutral", "Target_Change": "$90"}, {"Date": "2020-10-26", "Rating": "Reiterated", "Organization": "Telsey Advisory Group", "Rating_Change": "Outperform", "Target_Change": "$85 to $88"}, {"Date": "2020-10-07", "Rating": "Downgrade", "Organization": "Barclays", "Rating_Change": "Overweight to Equal Weight", "Target_Change": "$71"}, {"Date": "2020-08-05", "Rating": "Reiterated", "Organization": "Telsey Advisory Group", "Rating_Change": "Outperform", "Target_Change": "$95 to $85"}, {"Date": "2020-05-28", "Rating": "Reiterated", "Organization": "Telsey Advisory Group", "Rating_Change": "Outperform", "Target_Change": "$88 to $95"}, {"Date": "2020-05-21", "Rating": "Reiterated", "Organization": "Telsey Advisory Group", "Rating_Change": "Outperform", "Target_Change": "$92 to $88"}, {"Date": "2020-05-07", "Rating": "Downgrade", "Organization": "Cowen", "Rating_Change": "Outperform to Market Perform", "Target_Change": "$88 to $76"}]}