{"Ticker": "SNA", "Company": "Snap-on", "Sector": "Industrials", "Updated": "2022-12-06", "Rating": [{"Date": "2022-12-06", "Rating": "Downgrade", "Organization": "Oppenheimer", "Rating_Change": "Outperform to Perform", "Target_Change": ""}, {"Date": "2022-06-10", "Rating": "Initiated", "Organization": "MKM Partners", "Rating_Change": "Neutral", "Target_Change": "$238"}, {"Date": "2021-09-17", "Rating": "Downgrade", "Organization": "BofA Securities", "Rating_Change": "Neutral to Underperform", "Target_Change": "$240"}, {"Date": "2020-10-20", "Rating": "Resumed", "Organization": "Robert W. Baird", "Rating_Change": "Neutral", "Target_Change": "$167"}, {"Date": "2020-10-19", "Rating": "Downgrade", "Organization": "Longbow", "Rating_Change": "Neutral to Underperform", "Target_Change": "$128"}, {"Date": "2020-09-16", "Rating": "Initiated", "Organization": "UBS", "Rating_Change": "Sell", "Target_Change": "$143"}, {"Date": "2019-04-16", "Rating": "Downgrade", "Organization": "BofA/Merrill", "Rating_Change": "Buy to Neutral", "Target_Change": "$168"}, {"Date": "2019-04-10", "Rating": "Downgrade", "Organization": "Robert W. Baird", "Rating_Change": "Outperform to Neutral", "Target_Change": "$186 to $160"}, {"Date": "2018-12-21", "Rating": "Initiated", "Organization": "BofA/Merrill", "Rating_Change": "Buy", "Target_Change": ""}, {"Date": "2018-07-24", "Rating": "Downgrade", "Organization": "Northcoast", "Rating_Change": "Buy to Neutral", "Target_Change": ""}, {"Date": "2017-10-23", "Rating": "Upgrade", "Organization": "Barrington Research", "Rating_Change": "Mkt Perform to Outperform", "Target_Change": ""}, {"Date": "2017-08-21", "Rating": "Downgrade", "Organization": "Longbow", "Rating_Change": "Buy to Neutral", "Target_Change": ""}, {"Date": "2017-07-11", "Rating": "Resumed", "Organization": "FBR & Co.", "Rating_Change": "Outperform", "Target_Change": "$205"}, {"Date": "2017-04-12", "Rating": "Initiated", "Organization": "Oppenheimer", "Rating_Change": "Outperform", "Target_Change": "$200"}, {"Date": "2017-02-03", "Rating": "Reiterated", "Organization": "Wunderlich", "Rating_Change": "Buy", "Target_Change": "$190 to $205"}, {"Date": "2016-06-28", "Rating": "Initiated", "Organization": "CL King", "Rating_Change": "Buy", "Target_Change": "$174"}, {"Date": "2015-10-20", "Rating": "Initiated", "Organization": "Jefferies", "Rating_Change": "Hold", "Target_Change": ""}, {"Date": "2015-10-05", "Rating": "Upgrade", "Organization": "Longbow", "Rating_Change": "Neutral to Buy", "Target_Change": ""}, {"Date": "2015-04-23", "Rating": "Reiterated", "Organization": "Wunderlich", "Rating_Change": "Buy", "Target_Change": "$160 to $180"}, {"Date": "2014-12-02", "Rating": "Reiterated", "Organization": "Wunderlich", "Rating_Change": "Buy", "Target_Change": "$140 to $160"}, {"Date": "2014-10-09", "Rating": "Initiated", "Organization": "Wunderlich", "Rating_Change": "Buy", "Target_Change": "$140"}, {"Date": "2012-07-20", "Rating": "Downgrade", "Organization": "Barrington Research", "Rating_Change": "Outperform to Mkt Perform", "Target_Change": ""}]}