{"AMD": {"Ticker": "AMD", "Company": "Advanced Micro Devices", "Sector": "Information Technology", "Updated": "2022-10-07", "Rating": [{"Date": "2022-10-07", "Rating": "Reiterated", "Organization": "Wells Fargo", "Rating_Change": "Overweight", "Target_Change": "$90 to $85"}, {"Date": "2022-10-07", "Rating": "Reiterated", "Organization": "Truist", "Rating_Change": "Hold", "Target_Change": "$107 to $70"}, {"Date": "2022-10-07", "Rating": "Reiterated", "Organization": "The Benchmark Company", "Rating_Change": "Buy", "Target_Change": "$135 to $95"}, {"Date": "2022-10-07", "Rating": "Reiterated", "Organization": "Stifel", "Rating_Change": "Buy", "Target_Change": "$122 to $100"}, {"Date": "2022-10-07", "Rating": "Reiterated", "Organization": "Robert W. Baird", "Rating_Change": "Neutral", "Target_Change": "$100 to $65"}, {"Date": "2022-10-07", "Rating": "Reiterated", "Organization": "Raymond James", "Rating_Change": "Strong Buy", "Target_Change": "$130 to $100"}, {"Date": "2022-10-07", "Rating": "Reiterated", "Organization": "Piper Sandler", "Rating_Change": "Overweight", "Target_Change": "$140 to $90"}, {"Date": "2022-10-07", "Rating": "Reiterated", "Organization": "Morgan Stanley", "Rating_Change": "Overweight", "Target_Change": "$95 to $86"}, {"Date": "2022-10-07", "Rating": "Reiterated", "Organization": "Mizuho", "Rating_Change": "Buy", "Target_Change": "$125 to $102"}, {"Date": "2022-10-07", "Rating": "Reiterated", "Organization": "KeyBanc Capital Markets", "Rating_Change": "Overweight", "Target_Change": "$130 to $100"}, {"Date": "2022-10-07", "Rating": "Reiterated", "Organization": "JP Morgan", "Rating_Change": "Neutral", "Target_Change": "$120 to $80"}, {"Date": "2022-10-07", "Rating": "Reiterated", "Organization": "Deutsche Bank", "Rating_Change": "Hold", "Target_Change": "$95 to $80"}, {"Date": "2022-10-07", "Rating": "Reiterated", "Organization": "Craig Hallum", "Rating_Change": "Buy", "Target_Change": "$130 to $76"}, {"Date": "2022-10-07", "Rating": "Reiterated", "Organization": "BofA Securities", "Rating_Change": "Buy", "Target_Change": "$100 to $90"}, {"Date": "2022-10-07", "Rating": "Reiterated", "Organization": "Barclays", "Rating_Change": "Equal Weight", "Target_Change": "$85 to $68"}, {"Date": "2022-09-08", "Rating": "Initiated", "Organization": "Stifel", "Rating_Change": "Buy", "Target_Change": "$122"}, {"Date": "2022-07-14", "Rating": "Upgrade", "Organization": "BMO Capital Markets", "Rating_Change": "Market Perform to Outperform", "Target_Change": "$100 to $115"}, {"Date": "2022-07-13", "Rating": "Reiterated", "Organization": "Susquehanna", "Rating_Change": "Positive", "Target_Change": "$140 to $120"}], "Score": 1.33, "Cumulative_Rating": "Outperform", "Number_of_Analysts": 18, "Period": "180 days", "Letter_Rating": "B", "Analists": ["KeyBanc Capital Markets", "BofA Securities", "Robert W. Baird", "Deutsche Bank", "BMO Capital Markets", "Stifel", "Craig Hallum", "Mizuho", "Raymond James", "Wells Fargo", "Morgan Stanley", "JP Morgan", "Barclays", "Susquehanna", "The Benchmark Company", "Truist", "Piper Sandler"], "Price_Target": 91.33}, "BIIB": {"Ticker": "BIIB", "Company": "Biogen", "Sector": "Health Care", "Updated": "2022-10-07", "Rating": [{"Date": "2022-10-07", "Rating": "Upgrade", "Organization": "Argus", "Rating_Change": "Hold to Buy", "Target_Change": "$300"}, {"Date": "2022-09-28", "Rating": "Upgrade", "Organization": "Robert W. Baird", "Rating_Change": "Neutral to Outperform", "Target_Change": "$224 to $340"}, {"Date": "2022-09-28", "Rating": "Upgrade", "Organization": "Mizuho", "Rating_Change": "Neutral to Buy", "Target_Change": "$207 to $270"}, {"Date": "2022-09-28", "Rating": "Upgrade", "Organization": "BMO Capital Markets", "Rating_Change": "Market Perform to Outperform", "Target_Change": "$217 to $360"}], "Score": 1.75, "Cumulative_Rating": "Significant Outperform", "Number_of_Analysts": 4, "Period": "180 days", "Letter_Rating": "A", "Analists": ["Robert W. Baird", "BMO Capital Markets", "Mizuho", "Argus"], "Price_Target": 317.5}, "CHRW": {"Ticker": "CHRW", "Company": "C. H. Robinson", "Sector": "Industrials", "Updated": "2022-10-07", "Rating": [{"Date": "2022-10-07", "Rating": "Downgrade", "Organization": "Citigroup", "Rating_Change": "Buy to Neutral", "Target_Change": "$123 to $107"}, {"Date": "2022-08-17", "Rating": "Downgrade", "Organization": "Vertical Research", "Rating_Change": "Hold to Sell", "Target_Change": "$104"}, {"Date": "2022-07-12", "Rating": "Downgrade", "Organization": "Wolfe Research", "Rating_Change": "Outperform to Peer Perform", "Target_Change": ""}], "Score": -1.67, "Cumulative_Rating": "Significant Underperform", "Number_of_Analysts": 3, "Period": "180 days", "Letter_Rating": "E", "Analists": ["Wolfe Research", "Vertical Research", "Citigroup"], "Price_Target": 105.5}, "FTNT": {"Ticker": "FTNT", "Company": "Fortinet", "Sector": "Information Technology", "Updated": "2022-10-07", "Rating": [{"Date": "2022-10-07", "Rating": "Initiated", "Organization": "SMBC Nikko", "Rating_Change": "Outperform", "Target_Change": "$70"}, {"Date": "2022-09-16", "Rating": "Initiated", "Organization": "MKM Partners", "Rating_Change": "Buy", "Target_Change": "$70"}, {"Date": "2022-09-15", "Rating": "Initiated", "Organization": "Jefferies", "Rating_Change": "Buy", "Target_Change": "$65"}, {"Date": "2022-09-08", "Rating": "Initiated", "Organization": "Cantor Fitzgerald", "Rating_Change": "Overweight", "Target_Change": "$70"}, {"Date": "2022-09-02", "Rating": "Initiated", "Organization": "Atlantic Equities", "Rating_Change": "Overweight", "Target_Change": "$76"}], "Score": 2.0, "Cumulative_Rating": "Significant Outperform", "Number_of_Analysts": 5, "Period": "180 days", "Letter_Rating": "A", "Analists": ["MKM Partners", "Atlantic Equities", "Jefferies", "SMBC Nikko", "Cantor Fitzgerald"], "Price_Target": 70.2}, "GS": {"Ticker": "GS", "Company": "Goldman Sachs", "Sector": "Financials", "Updated": "2022-10-07", "Rating": [{"Date": "2022-10-07", "Rating": "Upgrade", "Organization": "Keefe Bruyette", "Rating_Change": "Mkt Perform to Outperform", "Target_Change": "$395 to $429"}, {"Date": "2022-10-05", "Rating": "Downgrade", "Organization": "Atlantic Equities", "Rating_Change": "Neutral to Underweight", "Target_Change": "$290"}, {"Date": "2022-09-06", "Rating": "Downgrade", "Organization": "Odeon", "Rating_Change": "Hold to Sell", "Target_Change": ""}], "Score": -0.33, "Cumulative_Rating": "Neutral", "Number_of_Analysts": 3, "Period": "180 days", "Letter_Rating": "C", "Analists": ["Atlantic Equities", "Odeon", "Keefe Bruyette"], "Price_Target": 359.5}, "HAL": {"Ticker": "HAL", "Company": "Halliburton", "Sector": "Energy", "Updated": "2022-10-07", "Rating": [{"Date": "2022-10-07", "Rating": "Resumed", "Organization": "Piper Sandler", "Rating_Change": "Overweight", "Target_Change": "$36"}], "Score": 2.0, "Cumulative_Rating": "Significant Outperform", "Number_of_Analysts": 1, "Period": "180 days", "Letter_Rating": "A", "Analists": ["Piper Sandler"], "Price_Target": 36.0}, "NSC": {"Ticker": "NSC", "Company": "Norfolk Southern", "Sector": "Industrials", "Updated": "2022-10-07", "Rating": [{"Date": "2022-10-07", "Rating": "Downgrade", "Organization": "Robert W. Baird", "Rating_Change": "Outperform to Neutral", "Target_Change": "$280 to $240"}, {"Date": "2022-09-28", "Rating": "Downgrade", "Organization": "Susquehanna", "Rating_Change": "Positive to Neutral", "Target_Change": "$275 to $218"}, {"Date": "2022-09-27", "Rating": "Downgrade", "Organization": "UBS", "Rating_Change": "Buy to Neutral", "Target_Change": ""}, {"Date": "2022-07-15", "Rating": "Upgrade", "Organization": "Stifel", "Rating_Change": "Hold to Buy", "Target_Change": "$289 to $275"}, {"Date": "2022-07-12", "Rating": "Downgrade", "Organization": "JP Morgan", "Rating_Change": "Overweight to Neutral", "Target_Change": "$306 to $258"}], "Score": -1.2, "Cumulative_Rating": "Underperform", "Number_of_Analysts": 5, "Period": "180 days", "Letter_Rating": "D", "Analists": ["Robert W. Baird", "Stifel", "JP Morgan", "UBS", "Susquehanna"], "Price_Target": 247.75}, "PFG": {"Ticker": "PFG", "Company": "Principal Financial Group", "Sector": "Financials", "Updated": "2022-10-07", "Rating": [{"Date": "2022-10-07", "Rating": "Downgrade", "Organization": "JP Morgan", "Rating_Change": "Neutral to Underweight", "Target_Change": "$69 to $72"}, {"Date": "2022-09-22", "Rating": "Initiated", "Organization": "Raymond James", "Rating_Change": "Mkt Perform", "Target_Change": ""}, {"Date": "2022-08-18", "Rating": "Downgrade", "Organization": "Credit Suisse", "Rating_Change": "Outperform to Neutral", "Target_Change": "$82 to $86"}], "Score": -1.0, "Cumulative_Rating": "Underperform", "Number_of_Analysts": 3, "Period": "180 days", "Letter_Rating": "D", "Analists": ["Credit Suisse", "JP Morgan", "Raymond James"], "Price_Target": 79.0}, "PGR": {"Ticker": "PGR", "Company": "Progressive Corporation", "Sector": "Financials", "Updated": "2022-10-07", "Rating": [{"Date": "2022-10-07", "Rating": "Upgrade", "Organization": "Jefferies", "Rating_Change": "Hold to Buy", "Target_Change": "$123 to $142"}], "Score": 1.0, "Cumulative_Rating": "Outperform", "Number_of_Analysts": 1, "Period": "180 days", "Letter_Rating": "B", "Analists": ["Jefferies"], "Price_Target": 142.0}, "SLB": {"Ticker": "SLB", "Company": "Schlumberger", "Sector": "Energy", "Updated": "2022-10-07", "Rating": [{"Date": "2022-10-07", "Rating": "Resumed", "Organization": "Piper Sandler", "Rating_Change": "Overweight", "Target_Change": "$50"}, {"Date": "2022-07-27", "Rating": "Upgrade", "Organization": "The Benchmark Company", "Rating_Change": "Hold to Buy", "Target_Change": "$55"}], "Score": 1.5, "Cumulative_Rating": "Significant Outperform", "Number_of_Analysts": 2, "Period": "180 days", "Letter_Rating": "A", "Analists": ["The Benchmark Company", "Piper Sandler"], "Price_Target": 52.5}, "ZION": {"Ticker": "ZION", "Company": "Zions Bancorp", "Sector": "Financials", "Updated": "2022-10-07", "Rating": [{"Date": "2022-10-07", "Rating": "Downgrade", "Organization": "Keefe Bruyette", "Rating_Change": "Outperform to Mkt Perform", "Target_Change": "$77 to $72"}, {"Date": "2022-09-28", "Rating": "Resumed", "Organization": "Wedbush", "Rating_Change": "Neutral", "Target_Change": "$61"}], "Score": -1.0, "Cumulative_Rating": "Underperform", "Number_of_Analysts": 2, "Period": "180 days", "Letter_Rating": "D", "Analists": ["Wedbush", "Keefe Bruyette"], "Price_Target": 66.5}}