{"ADSK": {"Ticker": "ADSK", "Company": "Autodesk", "Sector": "Information Technology", "Updated": "2022-02-25", "Rating": [{"Date": "2022-02-25", "Rating": "Reiterated", "Organization": "Stifel", "Rating_Change": "Buy", "Target_Change": "$310 to $285"}, {"Date": "2022-02-25", "Rating": "Reiterated", "Organization": "RBC Capital Mkts", "Rating_Change": "Outperform", "Target_Change": "$300 to $295"}, {"Date": "2022-02-25", "Rating": "Reiterated", "Organization": "Morgan Stanley", "Rating_Change": "Equal-Weight", "Target_Change": "$277 to $258"}, {"Date": "2022-02-25", "Rating": "Reiterated", "Organization": "KeyBanc Capital Markets", "Rating_Change": "Overweight", "Target_Change": "$300 to $260"}, {"Date": "2022-02-25", "Rating": "Reiterated", "Organization": "JP Morgan", "Rating_Change": "Overweight", "Target_Change": "$355 to $275"}, {"Date": "2022-02-25", "Rating": "Reiterated", "Organization": "Griffin Securities", "Rating_Change": "Buy", "Target_Change": "$340 to $300"}, {"Date": "2022-02-25", "Rating": "Reiterated", "Organization": "Goldman", "Rating_Change": "Sell", "Target_Change": "$250 to $220"}, {"Date": "2022-02-25", "Rating": "Reiterated", "Organization": "Deutsche Bank", "Rating_Change": "Buy", "Target_Change": "$330 to $275"}, {"Date": "2022-02-25", "Rating": "Reiterated", "Organization": "Citigroup", "Rating_Change": "Buy", "Target_Change": "$305 to $286"}, {"Date": "2022-02-22", "Rating": "Reiterated", "Organization": "RBC Capital Mkts", "Rating_Change": "Outperform", "Target_Change": "$343 to $300"}, {"Date": "2022-02-17", "Rating": "Resumed", "Organization": "Citigroup", "Rating_Change": "Buy", "Target_Change": "$305"}], "Score": 1.45, "Cumulative_Rating": "Outperform", "Number_of_Analysts": 11, "Period": "180 days", "Analists": ["Griffin Securities", "Stifel", "JP Morgan", "KeyBanc Capital Markets", "RBC Capital Mkts", "Morgan Stanley", "Citigroup", "Goldman", "Deutsche Bank"], "Price_Target": 278.09}, "DISH": {"Ticker": "DISH", "Company": "Dish Network", "Sector": "Communication Services", "Updated": "2022-02-25", "Rating": [{"Date": "2022-02-25", "Rating": "Upgrade", "Organization": "JP Morgan", "Rating_Change": "Underweight to Overweight", "Target_Change": "$42 to $40"}, {"Date": "2022-02-25", "Rating": "Reiterated", "Organization": "Truist", "Rating_Change": "Hold", "Target_Change": "$40 to $32"}, {"Date": "2022-02-25", "Rating": "Reiterated", "Organization": "Raymond James", "Rating_Change": "Strong Buy", "Target_Change": "$52 to $49"}, {"Date": "2022-02-25", "Rating": "Reiterated", "Organization": "Deutsche Bank", "Rating_Change": "Buy", "Target_Change": "$71 to $67"}, {"Date": "2022-02-25", "Rating": "Reiterated", "Organization": "Cowen", "Rating_Change": "Outperform", "Target_Change": "$55 to $53"}], "Score": 1.4, "Cumulative_Rating": "Outperform", "Number_of_Analysts": 5, "Period": "180 days", "Analists": ["Raymond James", "Truist", "JP Morgan", "Deutsche Bank", "Cowen"], "Price_Target": 48.2}, "DG": {"Ticker": "DG", "Company": "Dollar General", "Sector": "Consumer Discretionary", "Updated": "2022-02-25", "Rating": [{"Date": "2022-02-25", "Rating": "Upgrade", "Organization": "Wells Fargo", "Rating_Change": "Equal Weight to Overweight", "Target_Change": "$220"}, {"Date": "2022-01-18", "Rating": "Downgrade", "Organization": "Morgan Stanley", "Rating_Change": "Overweight to Equal-Weight", "Target_Change": "$250 to $225"}, {"Date": "2022-01-13", "Rating": "Initiated", "Organization": "Truist", "Rating_Change": "Hold", "Target_Change": "$28"}, {"Date": "2022-01-06", "Rating": "Downgrade", "Organization": "Wells Fargo", "Rating_Change": "Overweight to Equal Weight", "Target_Change": "$220"}], "Score": -0.5, "Cumulative_Rating": "Neutral", "Number_of_Analysts": 4, "Period": "180 days", "Analists": ["Wells Fargo", "Morgan Stanley", "Truist"], "Price_Target": 173.25}, "HD": {"Ticker": "HD", "Company": "Home Depot", "Sector": "Consumer Discretionary", "Updated": "2022-02-25", "Rating": [{"Date": "2022-02-25", "Rating": "Upgrade", "Organization": "Edward Jones", "Rating_Change": "Hold to Buy", "Target_Change": ""}, {"Date": "2022-02-23", "Rating": "Reiterated", "Organization": "UBS", "Rating_Change": "Buy", "Target_Change": "$470 to $430"}, {"Date": "2022-02-23", "Rating": "Reiterated", "Organization": "Truist", "Rating_Change": "Buy", "Target_Change": "$448 to $405"}, {"Date": "2022-02-23", "Rating": "Reiterated", "Organization": "Telsey Advisory Group", "Rating_Change": "Outperform", "Target_Change": "$425 to $375"}, {"Date": "2022-02-23", "Rating": "Reiterated", "Organization": "Raymond James", "Rating_Change": "Outperform", "Target_Change": "$420 to $350"}, {"Date": "2022-02-23", "Rating": "Reiterated", "Organization": "Jefferies", "Rating_Change": "Buy", "Target_Change": "$455 to $420"}, {"Date": "2022-02-23", "Rating": "Reiterated", "Organization": "Guggenheim", "Rating_Change": "Buy", "Target_Change": "$425 to $400"}, {"Date": "2022-02-23", "Rating": "Reiterated", "Organization": "Goldman", "Rating_Change": "Buy", "Target_Change": "$413 to $402"}, {"Date": "2022-02-23", "Rating": "Reiterated", "Organization": "Citigroup", "Rating_Change": "Buy", "Target_Change": "$445 to $377"}, {"Date": "2022-01-13", "Rating": "Upgrade", "Organization": "Truist", "Rating_Change": "Hold to Buy", "Target_Change": "$420 to $448"}, {"Date": "2021-12-06", "Rating": "Upgrade", "Organization": "Oppenheimer", "Rating_Change": "Perform to Outperform", "Target_Change": "$470"}], "Score": 1.73, "Cumulative_Rating": "Significant Outperform", "Number_of_Analysts": 11, "Period": "180 days", "Analists": ["Raymond James", "Truist", "Guggenheim", "Edward Jones", "UBS", "Goldman", "Citigroup", "Jefferies", "Oppenheimer", "Telsey Advisory Group"], "Price_Target": 369.64}, "INTU": {"Ticker": "INTU", "Company": "Intuit", "Sector": "Information Technology", "Updated": "2022-02-25", "Rating": [{"Date": "2022-02-25", "Rating": "Reiterated", "Organization": "Wolfe Research", "Rating_Change": "Outperform", "Target_Change": "$790 to $600"}, {"Date": "2022-02-25", "Rating": "Reiterated", "Organization": "Stifel", "Rating_Change": "Buy", "Target_Change": "$725 to $600"}, {"Date": "2022-02-25", "Rating": "Reiterated", "Organization": "JP Morgan", "Rating_Change": "Overweight", "Target_Change": "$750 to $640"}, {"Date": "2022-02-25", "Rating": "Reiterated", "Organization": "Jefferies", "Rating_Change": "Buy", "Target_Change": "$790 to $700"}, {"Date": "2022-02-25", "Rating": "Reiterated", "Organization": "Goldman", "Rating_Change": "Buy", "Target_Change": "$840 to $715"}, {"Date": "2022-02-25", "Rating": "Reiterated", "Organization": "Evercore ISI", "Rating_Change": "Outperform", "Target_Change": "$720 to $645"}, {"Date": "2022-02-25", "Rating": "Reiterated", "Organization": "Deutsche Bank", "Rating_Change": "Buy", "Target_Change": "$700 to $650"}, {"Date": "2022-02-25", "Rating": "Reiterated", "Organization": "BofA Securities", "Rating_Change": "Buy", "Target_Change": "$750 to $650"}, {"Date": "2022-02-25", "Rating": "Reiterated", "Organization": "BMO Capital Markets", "Rating_Change": "Outperform", "Target_Change": "$625 to $600"}, {"Date": "2022-02-01", "Rating": "Initiated", "Organization": "BMO Capital Markets", "Rating_Change": "Outperform", "Target_Change": "$625"}], "Score": 2.0, "Cumulative_Rating": "Significant Outperform", "Number_of_Analysts": 10, "Period": "180 days", "Analists": ["Stifel", "Evercore ISI", "Jefferies", "BofA Securities", "Wolfe Research", "JP Morgan", "Goldman", "Deutsche Bank", "BMO Capital Markets"], "Price_Target": 642.5}, "IRM": {"Ticker": "IRM", "Company": "Iron Mountain", "Sector": "Real Estate", "Updated": "2022-02-25", "Rating": [{"Date": "2022-02-25", "Rating": "Upgrade", "Organization": "Stifel", "Rating_Change": "Hold to Buy", "Target_Change": "$49 to $52"}], "Score": 1.0, "Cumulative_Rating": "Outperform", "Number_of_Analysts": 1, "Period": "180 days", "Analists": ["Stifel"], "Price_Target": 52.0}, "MNST": {"Ticker": "MNST", "Company": "Monster Beverage", "Sector": "Consumer Staples", "Updated": "2022-02-25", "Rating": [{"Date": "2022-02-25", "Rating": "Reiterated", "Organization": "JP Morgan", "Rating_Change": "Neutral", "Target_Change": "$93 to $90"}, {"Date": "2022-02-25", "Rating": "Reiterated", "Organization": "Guggenheim", "Rating_Change": "Buy", "Target_Change": "$109 to $105"}, {"Date": "2022-02-25", "Rating": "Reiterated", "Organization": "Deutsche Bank", "Rating_Change": "Buy", "Target_Change": "$107 to $105"}, {"Date": "2022-02-25", "Rating": "Reiterated", "Organization": "Cowen", "Rating_Change": "Market Perform", "Target_Change": "$92 to $90"}, {"Date": "2022-02-25", "Rating": "Reiterated", "Organization": "Citigroup", "Rating_Change": "Buy", "Target_Change": "$110 to $98"}, {"Date": "2022-02-17", "Rating": "Initiated", "Organization": "BMO Capital Markets", "Rating_Change": "Market Perform", "Target_Change": "$92"}], "Score": 1.0, "Cumulative_Rating": "Outperform", "Number_of_Analysts": 6, "Period": "180 days", "Analists": ["Guggenheim", "JP Morgan", "Deutsche Bank", "Citigroup", "Cowen", "BMO Capital Markets"], "Price_Target": 96.67}, "SEE": {"Ticker": "SEE", "Company": "Sealed Air", "Sector": "Materials", "Updated": "2022-02-25", "Rating": [{"Date": "2022-02-25", "Rating": "Downgrade", "Organization": "JP Morgan", "Rating_Change": "Overweight to Neutral", "Target_Change": "$71"}, {"Date": "2022-01-28", "Rating": "Initiated", "Organization": "Credit Suisse", "Rating_Change": "Outperform", "Target_Change": "$80"}, {"Date": "2022-01-20", "Rating": "Upgrade", "Organization": "Morgan Stanley", "Rating_Change": "Equal-Weight to Overweight", "Target_Change": "$61 to $79"}, {"Date": "2022-01-04", "Rating": "Downgrade", "Organization": "Robert W. Baird", "Rating_Change": "Outperform to Neutral", "Target_Change": "$72"}], "Score": 0.0, "Cumulative_Rating": "Neutral", "Number_of_Analysts": 4, "Period": "180 days", "Analists": ["Morgan Stanley", "Robert W. Baird", "JP Morgan", "Credit Suisse"], "Price_Target": 75.5}, "TSLA": {"Ticker": "TSLA", "Company": "Tesla", "Sector": "Consumer Discretionary", "Updated": "2022-02-25", "Rating": [{"Date": "2022-02-25", "Rating": "Upgrade", "Organization": "Daiwa Securities", "Rating_Change": "Neutral to Outperform", "Target_Change": "$980 to $900"}, {"Date": "2022-01-31", "Rating": "Upgrade", "Organization": "Credit Suisse", "Rating_Change": "Neutral to Outperform", "Target_Change": "$1025"}, {"Date": "2022-01-27", "Rating": "Reiterated", "Organization": "Wells Fargo", "Rating_Change": "Equal Weight", "Target_Change": "$860 to $910"}, {"Date": "2022-01-27", "Rating": "Reiterated", "Organization": "Robert W. Baird", "Rating_Change": "Outperform", "Target_Change": "$888 to $1108"}, {"Date": "2022-01-27", "Rating": "Reiterated", "Organization": "Oppenheimer", "Rating_Change": "Outperform", "Target_Change": "$1080 to $1103"}, {"Date": "2022-01-27", "Rating": "Reiterated", "Organization": "JP Morgan", "Rating_Change": "Underweight", "Target_Change": "$295 to $325"}, {"Date": "2022-01-27", "Rating": "Reiterated", "Organization": "Cowen", "Rating_Change": "Market Perform", "Target_Change": "$625 to $660"}, {"Date": "2022-01-27", "Rating": "Reiterated", "Organization": "Citigroup", "Rating_Change": "Sell", "Target_Change": "$262 to $313"}, {"Date": "2022-01-05", "Rating": "Reiterated", "Organization": "Barclays", "Rating_Change": "Underweight", "Target_Change": "$300 to $325"}, {"Date": "2022-01-03", "Rating": "Reiterated", "Organization": "RBC Capital Mkts", "Rating_Change": "Sector Perform", "Target_Change": "$950 to $1005"}, {"Date": "2021-12-30", "Rating": "Reiterated", "Organization": "Citigroup", "Rating_Change": "Sell", "Target_Change": "$236 to $262"}, {"Date": "2021-12-20", "Rating": "Initiated", "Organization": "Guggenheim", "Rating_Change": "Neutral", "Target_Change": "$924"}, {"Date": "2021-12-07", "Rating": "Reiterated", "Organization": "UBS", "Rating_Change": "Neutral", "Target_Change": "$725 to $1000"}], "Score": 0.15, "Cumulative_Rating": "Neutral", "Number_of_Analysts": 13, "Period": "180 days", "Analists": ["Robert W. Baird", "Daiwa Securities", "Barclays", "Credit Suisse", "Guggenheim", "Wells Fargo", "JP Morgan", "UBS", "Cowen", "RBC Capital Mkts", "Citigroup", "Oppenheimer"], "Price_Target": 758.46}, "UAA": {"Ticker": "UAA", "Company": "Under Armour (Class A)", "Sector": "Consumer Discretionary", "Updated": "2022-02-25", "Rating": [{"Date": "2022-02-25", "Rating": "Upgrade", "Organization": "BTIG Research", "Rating_Change": "Sell to Neutral", "Target_Change": ""}, {"Date": "2022-02-24", "Rating": "Upgrade", "Organization": "Argus", "Rating_Change": "Hold to Buy", "Target_Change": "$19"}, {"Date": "2022-02-02", "Rating": "Upgrade", "Organization": "Morgan Stanley", "Rating_Change": "Equal-Weight to Overweight", "Target_Change": "$23 to $24"}, {"Date": "2022-01-21", "Rating": "Upgrade", "Organization": "Citigroup", "Rating_Change": "Neutral to Buy", "Target_Change": "$29"}, {"Date": "2022-01-19", "Rating": "Upgrade", "Organization": "Exane BNP Paribas", "Rating_Change": "Underperform to Neutral", "Target_Change": "$18"}, {"Date": "2022-01-18", "Rating": "Upgrade", "Organization": "BMO Capital Markets", "Rating_Change": "Market Perform to Outperform", "Target_Change": "$23 to $25"}, {"Date": "2022-01-18", "Rating": "Initiated", "Organization": "Seaport Research Partners", "Rating_Change": "Neutral", "Target_Change": ""}, {"Date": "2022-01-04", "Rating": "Upgrade", "Organization": "Robert W. Baird", "Rating_Change": "Neutral to Outperform", "Target_Change": "$32"}, {"Date": "2021-12-16", "Rating": "Initiated", "Organization": "Truist", "Rating_Change": "Hold", "Target_Change": "$24"}, {"Date": "2021-12-16", "Rating": "Downgrade", "Organization": "Stifel", "Rating_Change": "Buy to Hold", "Target_Change": "$30 to $24"}, {"Date": "2021-12-15", "Rating": "Resumed", "Organization": "Wells Fargo", "Rating_Change": "Overweight", "Target_Change": "$33"}], "Score": 1.18, "Cumulative_Rating": "Outperform", "Number_of_Analysts": 11, "Period": "180 days", "Analists": ["Exane BNP Paribas", "Robert W. Baird", "Truist", "Stifel", "Wells Fargo", "Seaport Research Partners", "Morgan Stanley", "BTIG Research", "Citigroup", "Argus", "BMO Capital Markets"], "Price_Target": 18.73}}