{"AAP": {"Ticker": "AAP", "Company": "Advance Auto Parts", "Sector": "Consumer Discretionary", "Updated": "2023-02-08", "Rating": [{"Date": "2023-02-08", "Rating": "Initiated", "Organization": "Barclays", "Rating_Change": "Underweight", "Target_Change": "$145"}, {"Date": "2023-01-12", "Rating": "Downgrade", "Organization": "Wedbush", "Rating_Change": "Outperform to Neutral", "Target_Change": "$145"}, {"Date": "2022-11-17", "Rating": "Downgrade", "Organization": "Truist", "Rating_Change": "Buy to Hold", "Target_Change": "$228 to $147"}, {"Date": "2022-11-17", "Rating": "Downgrade", "Organization": "Guggenheim", "Rating_Change": "Buy to Neutral", "Target_Change": ""}, {"Date": "2022-11-17", "Rating": "Downgrade", "Organization": "Citigroup", "Rating_Change": "Buy to Neutral", "Target_Change": "$216 to $161"}, {"Date": "2022-11-16", "Rating": "Downgrade", "Organization": "UBS", "Rating_Change": "Buy to Neutral", "Target_Change": "$230 to $182"}], "Score": -1.17, "Cumulative_Rating": "Underperform", "Number_of_Analysts": 6, "Period": "180 days", "Letter_Rating": "D", "Analists": ["Barclays", "UBS", "Wedbush", "Guggenheim", "Citigroup", "Truist"], "Price_Target": 156.0}, "AAL": {"Ticker": "AAL", "Company": "American Airlines Group", "Sector": "Industrials", "Updated": "2023-02-08", "Rating": [{"Date": "2023-02-08", "Rating": "Upgrade", "Organization": "Redburn", "Rating_Change": "Neutral to Buy", "Target_Change": "$25"}, {"Date": "2022-12-16", "Rating": "Resumed", "Organization": "Goldman", "Rating_Change": "Neutral", "Target_Change": "$13"}], "Score": 1.0, "Cumulative_Rating": "Outperform", "Number_of_Analysts": 2, "Period": "180 days", "Letter_Rating": "B", "Analists": ["Goldman", "Redburn"], "Price_Target": 19.0}, "AXP": {"Ticker": "AXP", "Company": "American Express", "Sector": "Financials", "Updated": "2023-02-08", "Rating": [{"Date": "2023-02-08", "Rating": "Upgrade", "Organization": "Morgan Stanley", "Rating_Change": "Equal-Weight to Overweight", "Target_Change": "$186"}, {"Date": "2023-01-05", "Rating": "Downgrade", "Organization": "Stephens", "Rating_Change": "Equal-Weight to Underweight", "Target_Change": "$134"}, {"Date": "2022-12-13", "Rating": "Resumed", "Organization": "Piper Sandler", "Rating_Change": "Neutral", "Target_Change": "$159"}, {"Date": "2022-11-29", "Rating": "Initiated", "Organization": "Redburn", "Rating_Change": "Neutral", "Target_Change": ""}, {"Date": "2022-11-21", "Rating": "Initiated", "Organization": "UBS", "Rating_Change": "Neutral", "Target_Change": "$168"}], "Score": 0.0, "Cumulative_Rating": "Neutral", "Number_of_Analysts": 5, "Period": "180 days", "Letter_Rating": "C", "Analists": ["UBS", "Redburn", "Morgan Stanley", "Piper Sandler", "Stephens"], "Price_Target": 161.75}, "AZO": {"Ticker": "AZO", "Company": "AutoZone", "Sector": "Consumer Discretionary", "Updated": "2023-02-08", "Rating": [{"Date": "2023-02-08", "Rating": "Initiated", "Organization": "Barclays", "Rating_Change": "Overweight", "Target_Change": "$2663"}, {"Date": "2023-01-09", "Rating": "Upgrade", "Organization": "Guggenheim", "Rating_Change": "Neutral to Buy", "Target_Change": "$2735"}, {"Date": "2022-12-14", "Rating": "Downgrade", "Organization": "BofA Securities", "Rating_Change": "Neutral to Underperform", "Target_Change": ""}, {"Date": "2022-12-07", "Rating": "Reiterated", "Organization": "MKM Partners", "Rating_Change": "Buy", "Target_Change": "$2350 to $2650"}], "Score": 1.0, "Cumulative_Rating": "Outperform", "Number_of_Analysts": 4, "Period": "180 days", "Letter_Rating": "B", "Analists": ["Guggenheim", "Barclays", "BofA Securities", "MKM Partners"], "Price_Target": 2682.67}, "BBY": {"Ticker": "BBY", "Company": "Best Buy", "Sector": "Consumer Discretionary", "Updated": "2023-02-08", "Rating": [{"Date": "2023-02-08", "Rating": "Initiated", "Organization": "Barclays", "Rating_Change": "Equal Weight", "Target_Change": "$88"}, {"Date": "2023-01-12", "Rating": "Downgrade", "Organization": "Exane BNP Paribas", "Rating_Change": "Outperform to Neutral", "Target_Change": ""}, {"Date": "2022-12-20", "Rating": "Initiated", "Organization": "Credit Suisse", "Rating_Change": "Neutral", "Target_Change": "$90"}, {"Date": "2022-12-14", "Rating": "Downgrade", "Organization": "BofA Securities", "Rating_Change": "Neutral to Underperform", "Target_Change": "$80 to $69"}, {"Date": "2022-12-12", "Rating": "Upgrade", "Organization": "Goldman", "Rating_Change": "Sell to Neutral", "Target_Change": "$59 to $83"}], "Score": -0.6, "Cumulative_Rating": "Underperform", "Number_of_Analysts": 5, "Period": "180 days", "Letter_Rating": "D", "Analists": ["Barclays", "Goldman", "BofA Securities", "Credit Suisse", "Exane BNP Paribas"], "Price_Target": 82.5}, "COST": {"Ticker": "COST", "Company": "Costco", "Sector": "Consumer Staples", "Updated": "2023-02-08", "Rating": [{"Date": "2023-02-08", "Rating": "Initiated", "Organization": "Barclays", "Rating_Change": "Equal Weight", "Target_Change": "$510"}, {"Date": "2022-12-20", "Rating": "Resumed", "Organization": "Credit Suisse", "Rating_Change": "Neutral", "Target_Change": "$550 to $520"}, {"Date": "2022-12-09", "Rating": "Reiterated", "Organization": "Telsey Advisory Group", "Rating_Change": "Outperform", "Target_Change": "$590 to $580"}, {"Date": "2022-12-06", "Rating": "Initiated", "Organization": "Bernstein", "Rating_Change": "Outperform", "Target_Change": "$586"}], "Score": 1.0, "Cumulative_Rating": "Outperform", "Number_of_Analysts": 4, "Period": "180 days", "Letter_Rating": "B", "Analists": ["Barclays", "Credit Suisse", "Bernstein", "Telsey Advisory Group"], "Price_Target": 549.0}, "DAL": {"Ticker": "DAL", "Company": "Delta Air Lines", "Sector": "Industrials", "Updated": "2023-02-08", "Rating": [{"Date": "2023-02-08", "Rating": "Upgrade", "Organization": "Redburn", "Rating_Change": "Neutral to Buy", "Target_Change": "$55"}, {"Date": "2023-01-05", "Rating": "Upgrade", "Organization": "Argus", "Rating_Change": "Hold to Buy", "Target_Change": "$39"}, {"Date": "2022-12-16", "Rating": "Resumed", "Organization": "Goldman", "Rating_Change": "Buy", "Target_Change": "$40"}, {"Date": "2022-12-15", "Rating": "Downgrade", "Organization": "Evercore ISI", "Rating_Change": "Outperform to In-line", "Target_Change": "$50 to $40"}], "Score": 0.75, "Cumulative_Rating": "Outperform", "Number_of_Analysts": 4, "Period": "180 days", "Letter_Rating": "B", "Analists": ["Goldman", "Evercore ISI", "Argus", "Redburn"], "Price_Target": 43.5}, "DFS": {"Ticker": "DFS", "Company": "Discover Financial Services", "Sector": "Financials", "Updated": "2023-02-08", "Rating": [{"Date": "2023-02-08", "Rating": "Downgrade", "Organization": "Morgan Stanley", "Rating_Change": "Overweight to Equal-Weight", "Target_Change": "$96"}, {"Date": "2023-01-06", "Rating": "Downgrade", "Organization": "Barclays", "Rating_Change": "Overweight to Equal Weight", "Target_Change": "$115 to $120"}, {"Date": "2022-12-13", "Rating": "Downgrade", "Organization": "BofA Securities", "Rating_Change": "Buy to Underperform", "Target_Change": ""}, {"Date": "2022-11-21", "Rating": "Initiated", "Organization": "UBS", "Rating_Change": "Neutral", "Target_Change": "$120"}], "Score": -1.0, "Cumulative_Rating": "Underperform", "Number_of_Analysts": 4, "Period": "180 days", "Letter_Rating": "D", "Analists": ["Barclays", "UBS", "BofA Securities", "Morgan Stanley"], "Price_Target": 112.0}, "DG": {"Ticker": "DG", "Company": "Dollar General", "Sector": "Consumer Discretionary", "Updated": "2023-02-08", "Rating": [{"Date": "2023-02-08", "Rating": "Initiated", "Organization": "Barclays", "Rating_Change": "Equal Weight", "Target_Change": "$237"}, {"Date": "2022-12-20", "Rating": "Initiated", "Organization": "Credit Suisse", "Rating_Change": "Neutral", "Target_Change": "$260"}, {"Date": "2022-12-02", "Rating": "Reiterated", "Organization": "Telsey Advisory Group", "Rating_Change": "Outperform", "Target_Change": "$285 to $270"}], "Score": 0.67, "Cumulative_Rating": "Outperform", "Number_of_Analysts": 3, "Period": "180 days", "Letter_Rating": "B", "Analists": ["Barclays", "Credit Suisse", "Telsey Advisory Group"], "Price_Target": 255.67}, "DLTR": {"Ticker": "DLTR", "Company": "Dollar Tree", "Sector": "Consumer Discretionary", "Updated": "2023-02-08", "Rating": [{"Date": "2023-02-08", "Rating": "Initiated", "Organization": "Barclays", "Rating_Change": "Equal Weight", "Target_Change": "$145"}, {"Date": "2023-01-24", "Rating": "Downgrade", "Organization": "Gordon Haskett", "Rating_Change": "Buy to Accumulate", "Target_Change": "$163"}, {"Date": "2022-12-20", "Rating": "Initiated", "Organization": "Credit Suisse", "Rating_Change": "Neutral", "Target_Change": "$150"}], "Score": -0.33, "Cumulative_Rating": "Neutral", "Number_of_Analysts": 3, "Period": "180 days", "Letter_Rating": "C", "Analists": ["Barclays", "Credit Suisse", "Gordon Haskett"], "Price_Target": 152.67}, "FTNT": {"Ticker": "FTNT", "Company": "Fortinet", "Sector": "Information Technology", "Updated": "2023-02-08", "Rating": [{"Date": "2023-02-08", "Rating": "Downgrade", "Organization": "KeyBanc Capital Markets", "Rating_Change": "Overweight to Sector Weight", "Target_Change": ""}, {"Date": "2023-02-07", "Rating": "Initiated", "Organization": "Loop Capital", "Rating_Change": "Buy", "Target_Change": "$66"}, {"Date": "2023-02-02", "Rating": "Downgrade", "Organization": "BMO Capital Markets", "Rating_Change": "Outperform to Market Perform", "Target_Change": "$58 to $57"}, {"Date": "2023-01-31", "Rating": "Reiterated", "Organization": "MKM Partners", "Rating_Change": "Buy", "Target_Change": "$70 to $65"}, {"Date": "2023-01-27", "Rating": "Downgrade", "Organization": "Mizuho", "Rating_Change": "Buy to Neutral", "Target_Change": "$60"}, {"Date": "2023-01-24", "Rating": "Initiated", "Organization": "JP Morgan", "Rating_Change": "Overweight", "Target_Change": "$69"}, {"Date": "2023-01-24", "Rating": "Initiated", "Organization": "Guggenheim", "Rating_Change": "Neutral", "Target_Change": ""}, {"Date": "2023-01-18", "Rating": "Initiated", "Organization": "Scotiabank", "Rating_Change": "Sector Outperform", "Target_Change": "$65"}, {"Date": "2023-01-13", "Rating": "Downgrade", "Organization": "BTIG Research", "Rating_Change": "Buy to Neutral", "Target_Change": ""}], "Score": 0.11, "Cumulative_Rating": "Neutral", "Number_of_Analysts": 9, "Period": "180 days", "Letter_Rating": "C", "Analists": ["Scotiabank", "BMO Capital Markets", "JP Morgan", "Mizuho", "Guggenheim", "BTIG Research", "KeyBanc Capital Markets", "Loop Capital", "MKM Partners"], "Price_Target": 63.67}, "HD": {"Ticker": "HD", "Company": "Home Depot", "Sector": "Consumer Discretionary", "Updated": "2023-02-08", "Rating": [{"Date": "2023-02-08", "Rating": "Initiated", "Organization": "Barclays", "Rating_Change": "Equal Weight", "Target_Change": "$323"}, {"Date": "2022-12-20", "Rating": "Resumed", "Organization": "Credit Suisse", "Rating_Change": "Neutral", "Target_Change": "$390 to $335"}, {"Date": "2022-12-06", "Rating": "Initiated", "Organization": "Bernstein", "Rating_Change": "Mkt Perform", "Target_Change": "$337"}, {"Date": "2022-11-16", "Rating": "Downgrade", "Organization": "Raymond James", "Rating_Change": "Outperform to Mkt Perform", "Target_Change": ""}], "Score": -0.5, "Cumulative_Rating": "Neutral", "Number_of_Analysts": 4, "Period": "180 days", "Letter_Rating": "C", "Analists": ["Raymond James", "Barclays", "Credit Suisse", "Bernstein"], "Price_Target": 331.67}, "LOW": {"Ticker": "LOW", "Company": "Lowe's", "Sector": "Consumer Discretionary", "Updated": "2023-02-08", "Rating": [{"Date": "2023-02-08", "Rating": "Initiated", "Organization": "Barclays", "Rating_Change": "Equal Weight", "Target_Change": "$215"}, {"Date": "2022-12-20", "Rating": "Initiated", "Organization": "Credit Suisse", "Rating_Change": "Neutral", "Target_Change": "$210"}, {"Date": "2022-12-06", "Rating": "Initiated", "Organization": "Bernstein", "Rating_Change": "Mkt Perform", "Target_Change": "$237"}], "Score": 0.0, "Cumulative_Rating": "Neutral", "Number_of_Analysts": 3, "Period": "180 days", "Letter_Rating": "C", "Analists": ["Barclays", "Credit Suisse", "Bernstein"], "Price_Target": 220.67}, "LUMN": {"Ticker": "LUMN", "Company": "Lumen Technologies", "Sector": "Communication Services", "Updated": "2023-02-08", "Rating": [{"Date": "2023-02-08", "Rating": "Downgrade", "Organization": "Citigroup", "Rating_Change": "Neutral to Sell", "Target_Change": "$6.25 to $3.50"}, {"Date": "2022-12-06", "Rating": "Resumed", "Organization": "Goldman", "Rating_Change": "Neutral", "Target_Change": "$6"}], "Score": -0.5, "Cumulative_Rating": "Neutral", "Number_of_Analysts": 2, "Period": "180 days", "Letter_Rating": "C", "Analists": ["Citigroup", "Goldman"], "Price_Target": 6.0}, "ORLY": {"Ticker": "ORLY", "Company": "O'Reilly Automotive", "Sector": "Consumer Discretionary", "Updated": "2023-02-08", "Rating": [{"Date": "2023-02-08", "Rating": "Initiated", "Organization": "Barclays", "Rating_Change": "Equal Weight", "Target_Change": "$815"}, {"Date": "2023-01-09", "Rating": "Resumed", "Organization": "Guggenheim", "Rating_Change": "Buy", "Target_Change": "$925893"}], "Score": 1.0, "Cumulative_Rating": "Outperform", "Number_of_Analysts": 2, "Period": "180 days", "Letter_Rating": "B", "Analists": ["Guggenheim", "Barclays"], "Price_Target": 463354.0}, "OMC": {"Ticker": "OMC", "Company": "Omnicom Group", "Sector": "Communication Services", "Updated": "2023-02-08", "Rating": [{"Date": "2023-02-08", "Rating": "Upgrade", "Organization": "Morgan Stanley", "Rating_Change": "Underweight to Equal-Weight", "Target_Change": "$85 to $95"}], "Score": 1.0, "Cumulative_Rating": "Outperform", "Number_of_Analysts": 1, "Period": "180 days", "Letter_Rating": "B", "Analists": ["Morgan Stanley"], "Price_Target": 95.0}, "RCL": {"Ticker": "RCL", "Company": "Royal Caribbean Group", "Sector": "Consumer Discretionary", "Updated": "2023-02-08", "Rating": [{"Date": "2023-02-08", "Rating": "Upgrade", "Organization": "BofA Securities", "Rating_Change": "Underperform to Neutral", "Target_Change": "$40 to $78"}, {"Date": "2023-01-10", "Rating": "Upgrade", "Organization": "Morgan Stanley", "Rating_Change": "Underweight to Equal-Weight", "Target_Change": "$40 to $50"}, {"Date": "2022-12-06", "Rating": "Downgrade", "Organization": "JP Morgan", "Rating_Change": "Overweight to Underweight", "Target_Change": "$106 to $47"}], "Score": 0.0, "Cumulative_Rating": "Neutral", "Number_of_Analysts": 3, "Period": "180 days", "Letter_Rating": "C", "Analists": ["JP Morgan", "BofA Securities", "Morgan Stanley"], "Price_Target": 58.33}, "SHW": {"Ticker": "SHW", "Company": "Sherwin-Williams", "Sector": "Materials", "Updated": "2023-02-08", "Rating": [{"Date": "2023-02-08", "Rating": "Downgrade", "Organization": "KeyBanc Capital Markets", "Rating_Change": "Overweight to Sector Weight", "Target_Change": ""}], "Score": -2.0, "Cumulative_Rating": "Significant Underperform", "Number_of_Analysts": 1, "Period": "180 days", "Letter_Rating": "E", "Analists": ["KeyBanc Capital Markets"], "Price_Target": 0}, "LUV": {"Ticker": "LUV", "Company": "Southwest Airlines", "Sector": "Industrials", "Updated": "2023-02-08", "Rating": [{"Date": "2023-02-08", "Rating": "Downgrade", "Organization": "Redburn", "Rating_Change": "Buy to Neutral", "Target_Change": "$40"}, {"Date": "2023-01-11", "Rating": "Downgrade", "Organization": "Susquehanna", "Rating_Change": "Positive to Neutral", "Target_Change": "$40"}, {"Date": "2022-12-16", "Rating": "Resumed", "Organization": "Goldman", "Rating_Change": "Neutral", "Target_Change": "$41"}], "Score": -1.0, "Cumulative_Rating": "Underperform", "Number_of_Analysts": 3, "Period": "180 days", "Letter_Rating": "D", "Analists": ["Susquehanna", "Goldman", "Redburn"], "Price_Target": 40.33}, "TGT": {"Ticker": "TGT", "Company": "Target Corporation", "Sector": "Consumer Discretionary", "Updated": "2023-02-08", "Rating": [{"Date": "2023-02-08", "Rating": "Initiated", "Organization": "Barclays", "Rating_Change": "Equal Weight", "Target_Change": "$163"}, {"Date": "2023-01-24", "Rating": "Initiated", "Organization": "Oppenheimer", "Rating_Change": "Outperform", "Target_Change": "$190"}, {"Date": "2023-01-04", "Rating": "Downgrade", "Organization": "Wells Fargo", "Rating_Change": "Overweight to Equal Weight", "Target_Change": "$170 to $142"}, {"Date": "2022-12-21", "Rating": "Downgrade", "Organization": "Gordon Haskett", "Rating_Change": "Buy to Hold", "Target_Change": "$132"}, {"Date": "2022-12-20", "Rating": "Downgrade", "Organization": "Credit Suisse", "Rating_Change": "Outperform to Neutral", "Target_Change": "$165 to $160"}, {"Date": "2022-12-12", "Rating": "Downgrade", "Organization": "Cleveland Research", "Rating_Change": "Buy to Neutral", "Target_Change": ""}, {"Date": "2022-12-06", "Rating": "Initiated", "Organization": "Bernstein", "Rating_Change": "Outperform", "Target_Change": "$190"}, {"Date": "2022-11-17", "Rating": "Upgrade", "Organization": "Piper Sandler", "Rating_Change": "Neutral to Overweight", "Target_Change": "$190 to $200"}, {"Date": "2022-11-17", "Rating": "Downgrade", "Organization": "Deutsche Bank", "Rating_Change": "Buy to Hold", "Target_Change": "$183 to $144"}, {"Date": "2022-11-17", "Rating": "Downgrade", "Organization": "BMO Capital Markets", "Rating_Change": "Outperform to Market Perform", "Target_Change": "$190 to $165"}], "Score": -0.3, "Cumulative_Rating": "Neutral", "Number_of_Analysts": 10, "Period": "180 days", "Letter_Rating": "C", "Analists": ["Deutsche Bank", "Barclays", "Wells Fargo", "BMO Capital Markets", "Oppenheimer", "Piper Sandler", "Bernstein", "Gordon Haskett", "Cleveland Research", "Credit Suisse"], "Price_Target": 165.11}, "TSCO": {"Ticker": "TSCO", "Company": "Tractor Supply Company", "Sector": "Consumer Discretionary", "Updated": "2023-02-08", "Rating": [{"Date": "2023-02-08", "Rating": "Initiated", "Organization": "Barclays", "Rating_Change": "Overweight", "Target_Change": "$254"}, {"Date": "2023-01-12", "Rating": "Upgrade", "Organization": "Exane BNP Paribas", "Rating_Change": "Neutral to Outperform", "Target_Change": ""}, {"Date": "2022-12-20", "Rating": "Initiated", "Organization": "Credit Suisse", "Rating_Change": "Outperform", "Target_Change": "$260"}], "Score": 2.0, "Cumulative_Rating": "Significant Outperform", "Number_of_Analysts": 3, "Period": "180 days", "Letter_Rating": "A", "Analists": ["Barclays", "Credit Suisse", "Exane BNP Paribas"], "Price_Target": 257.0}, "UAL": {"Ticker": "UAL", "Company": "United Airlines", "Sector": "Industrials", "Updated": "2023-02-08", "Rating": [{"Date": "2023-02-08", "Rating": "Upgrade", "Organization": "Redburn", "Rating_Change": "Sell to Neutral", "Target_Change": "$55"}, {"Date": "2022-12-16", "Rating": "Resumed", "Organization": "Goldman", "Rating_Change": "Buy", "Target_Change": "$51"}, {"Date": "2022-12-06", "Rating": "Upgrade", "Organization": "Argus", "Rating_Change": "Hold to Buy", "Target_Change": "$52"}, {"Date": "2022-12-05", "Rating": "Upgrade", "Organization": "Morgan Stanley", "Rating_Change": "Equal-Weight to Overweight", "Target_Change": "$67"}], "Score": 1.5, "Cumulative_Rating": "Significant Outperform", "Number_of_Analysts": 4, "Period": "180 days", "Letter_Rating": "A", "Analists": ["Morgan Stanley", "Argus", "Goldman", "Redburn"], "Price_Target": 56.25}, "URI": {"Ticker": "URI", "Company": "United Rentals", "Sector": "Industrials", "Updated": "2023-02-08", "Rating": [{"Date": "2023-02-08", "Rating": "Initiated", "Organization": "Credit Suisse", "Rating_Change": "Outperform", "Target_Change": "$544"}], "Score": 2.0, "Cumulative_Rating": "Significant Outperform", "Number_of_Analysts": 1, "Period": "180 days", "Letter_Rating": "A", "Analists": ["Credit Suisse"], "Price_Target": 544.0}, "WMT": {"Ticker": "WMT", "Company": "Walmart", "Sector": "Consumer Staples", "Updated": "2023-02-08", "Rating": [{"Date": "2023-02-08", "Rating": "Initiated", "Organization": "Barclays", "Rating_Change": "Overweight", "Target_Change": "$159"}, {"Date": "2023-01-26", "Rating": "Upgrade", "Organization": "Tigress Financial", "Rating_Change": "Neutral to Buy", "Target_Change": "$170 to $176"}, {"Date": "2022-12-20", "Rating": "Resumed", "Organization": "Credit Suisse", "Rating_Change": "Outperform", "Target_Change": "$160 to $170"}, {"Date": "2022-12-06", "Rating": "Initiated", "Organization": "Bernstein", "Rating_Change": "Mkt Perform", "Target_Change": "$159"}], "Score": 1.5, "Cumulative_Rating": "Significant Outperform", "Number_of_Analysts": 4, "Period": "180 days", "Letter_Rating": "A", "Analists": ["Barclays", "Credit Suisse", "Bernstein", "Tigress Financial"], "Price_Target": 166.0}}